uniprot_lb_poo/__init__.py
uniprot_lb_poo/hello.py
uniprot_lb_poo/uniprot.py
uniprot_lb_poo/uniprot_collection.py
uniprot_lb_poo-0.1.9.dist-info/METADATA
uniprot_lb_poo-0.1.9.dist-info/WHEEL
uniprot_lb_poo-0.1.9.dist-info/RECORD
