Metadata-Version: 2.3
Name: uniprot_lb_poo
Version: 0.1.9
Summary: Parses uniprot entries (from uniprot files) and creates Uniprot objects
Project-URL: HomePage, http://pedago-service.univ-lyon1.fr:2325/briou/uniprot.git
Project-URL: DOWNLOAD, http://pedago-service.univ-lyon1.fr:2325/briou/uniprot/-/archive/publish/uniprot-master.tar.gz
Author-email: Baptiste RIOU & Lorcan BRENDERS <baptiste.riou2@etu.univ-lyon1.fr>
Maintainer-email: Guillaume LAUNAY & Arnaud MARY <guillaume.launay@univ-lyon1.fr>
Keywords: Bioinformatics,Parser,Protein,Uniprot
Requires-Python: >=3.10
Requires-Dist: matplotlib>=3.9.2
